{
  "name": "NanoMatter",
  "slug": "nanomatter",
  "website": "https://nano-matter.com/",
  "description": "NanoMatter is the leader in the physics intelligence high yield semiconductor manufacturing",
  "one_liner": "NanoMatter is the leader in the physics intelligence high yield semiconductor manufacturing",
  "location": "Berlin, Germany",
  "industry": "Manufacturing",
  "industry_slug": "manufacturing",
  "subindustry": "",
  "status": "Active",
  "logo_url": "",
  "social_media": {},
  "is_billion_plus": false,
  "is_in_program": false,
  "is_bcorp": false,
  "tags": [],
  "url": "https://www.techstars.com/portfolio/nanomatter",
  "api": "/api/companies/nanomatter.json"
}